stcube/__init__.py
stcube/_ds_ioc.py
stcube/_ds_ld.py
stcube/_ds_tv.py
stcube/_fnc_body.py
stcube/_fnc_library.py
stcube/_fnc_modules.py
stcube/_fnc_repo.py
stcube/_pyqt_pack.py
stcube/core.py
stcube/main.py
stcube/test.py
stcube-0.2.1.dist-info/METADATA
stcube-0.2.1.dist-info/WHEEL
stcube-0.2.1.dist-info/entry_points.txt
stcube-0.2.1.dist-info/top_level.txt
stcube-0.2.1.dist-info/RECORD
