Metadata-Version: 2.1
Name: stcube
Version: 0.2.1
Summary: used to manage stm32cubemx template project and some user source file.
Author-email: 2229066748@qq.com
Maintainer: Eagle'sBaby
Maintainer-email: 2229066748@qq.com
License: Apache Licence 2.0
Keywords: management,stm32cubemx
Classifier: Programming Language :: Python :: 3
Classifier: Operating System :: Microsoft :: Windows
Requires-Python: >=3.10
